saneyak/__init__.py
saneyak/py.typed
saneyak-0.1.0rc1.dist-info/WHEEL
saneyak-0.1.0rc1.dist-info/METADATA
saneyak-0.1.0rc1.dist-info/RECORD
